screenshotone/__init__.py
screenshotone/sdk.py
screenshotone-0.0.16.dist-info/METADATA
screenshotone-0.0.16.dist-info/WHEEL
screenshotone-0.0.16.dist-info/licenses/LICENSE
screenshotone-0.0.16.dist-info/RECORD
