Metadata-Version: 2.4
Name: screenshotone
Version: 0.0.16
Summary: A Python SDK for ScreenshotOne.com API to take screenshots of URLs, render HTML as images and PDF
Project-URL: Homepage, https://screenshotone.com/
Project-URL: Docs, https://screenshotone.com/docs/getting-started/
Author-email: Dmytro Krasun <support@screenshotone.com>
License-File: LICENSE
Classifier: License :: OSI Approved :: MIT License
Classifier: Operating System :: OS Independent
Classifier: Programming Language :: Python :: 3
Requires-Python: >=3.7
Requires-Dist: requests>=2.28.1
